[{"Google Play": {"importance": 88, "level": -1}, "app store": {"importance": 14, "level": -1}, "Android operating system": {"importance": 10, "level": -1}, "ChromeOS": {"importance": 21, "level": -1}, "Android": {"importance": 50, "level": -1}, "Google Play Store": {"importance": 36, "level": -1}, "March 6, 2012": {"importance": 3, "level": -1}, "Android Market": {"importance": 24, "level": -1}, "Google Music": {"importance": 4, "level": -1}, "Google Movies": {"importance": 2, "level": -1}, "Google eBookstore": {"importance": 5, "level": -1}, "YouTube Music": {"importance": 8, "level": -1}, "2020": {"importance": 7, "level": -1}, "Play Music": {"importance": 2, "level": -1}, "December 6, 2010": {"importance": 2, "level": -1}, "November 2011": {"importance": 1, "level": -1}, "Google": {"importance": 193, "level": -1}, "online music locker": {"importance": 4, "level": -1}, "Google Podcasts": {"importance": 1, "level": -1}, "Google Play Newsstand": {"importance": 4, "level": -1}, "Google News": {"importance": 14, "level": -1}, "Google News & Weather": {"importance": 6, "level": -1}, "May 15, 2018": {"importance": 3, "level": -1}, "news aggregator": {"importance": 1, "level": -1}, "Google Store": {"importance": 3, "level": -1}, "March 11, 2015": {"importance": 3, "level": -1}, "Google Nexus": {"importance": 2, "level": -1}, "Chromecast": {"importance": 3, "level": -1}, "St. Patrick's Cathedral": {"importance": 6, "level": -1}, "St. Paul's Cathedral": {"importance": 2, "level": -1}, "Free App of the Week": {"importance": 2, "level": -1}, "March 2017": {"importance": 2, "level": -1}, "fitness": {"importance": 3, "level": -1}, "themes": {"importance": 3, "level": -1}, "theme": {"importance": 1, "level": -1}, "puzzle game": {"importance": 1, "level": -1}, "February 2011": {"importance": 1, "level": -1}, "Google Play Console": {"importance": 1, "level": -1}, "Android app": {"importance": 1, "level": -1}, "Material Design": {"importance": 2, "level": -1}, "design language": {"importance": 2, "level": -1}, "Play apps": {"importance": 2, "level": -1}, "PNG": {"importance": 3, "level": -1}, "WebP": {"importance": 2, "level": -1}, "WebP format": {"importance": 1, "level": -1}, "Google Play Instant": {"importance": 2, "level": -1}, "2017": {"importance": 3, "level": -1}, "Google Instant": {"importance": 1, "level": -1}, "Google Play payment system": {"importance": 2, "level": -1}, "February 13, 2009": {"importance": 2, "level": -1}, "September 2014": {"importance": 1, "level": -1}, "China UnionPay": {"importance": 1, "level": -1}, "China": {"importance": 1, "level": -1}, "Hong Kong": {"importance": 2, "level": -1}, "Macau": {"importance": 2, "level": -1}, "Google Play gift cards": {"importance": 1, "level": -1}, "August 21, 2012": {"importance": 1, "level": -1}, "change of the same model": {"importance": 2, "level": -1}, "Apple": {"importance": 1, "level": -1}, "Apple's": {"importance": 1, "level": -1}, "January 1, 2018": {"importance": 1, "level": -1}, "App Store": {"importance": 1, "level": -1}, "": {"importance": 1, "level": -1}, "Microsoft Windows": {"importance": 1, "level": -1}, "Android Open Source Project": {"importance": 1, "level": -1}, "Google Play Awards": {"importance": 1, "level": -1}, "April 2016": {"importance": 1, "level": -1}, "Google Play Services": {"importance": 2, "level": -1}, "API": {"importance": 1, "level": -1}, "Android 2.2 \"Froyo\"": {"importance": 1, "level": -1}, "Disney+": {"importance": 1, "level": -1}, "June 2017": {"importance": 3, "level": -1}, "ESRB": {"importance": 1, "level": -1}, "ratings authority": {"importance": 1, "level": -1}, "PEGI": {"importance": 3, "level": -1}, "Europe": {"importance": 3, "level": -1}, "Play Store": {"importance": 7, "level": -1}, "Gro": {"importance": 1, "level": -1}, "Grooveshark": {"importance": 3, "level": -1}, "App Market": {"importance": 2, "level": -1}, "Android Marshmallow": {"importance": 1, "level": -1}, "spyware": {"importance": 4, "level": -1}, "malware": {"importance": 9, "level": -1}, "Google Bouncer": {"importance": 1, "level": -1}, "February 2012": {"importance": 2, "level": -1}, "Play Protect": {"importance": 1, "level": -1}, "trojan horses": {"importance": 1, "level": -1}, "trojan horse": {"importance": 1, "level": -1}, "DroidDream": {"importance": 3, "level": -1}, "exploit": {"importance": 1, "level": -1}, "rootkit exploit": {"importance": 1, "level": -1}, "rootkit": {"importance": 1, "level": -1}, "Gingerbread": {"importance": 3, "level": -1}, "IMSI": {"importance": 1, "level": -1}, "IMEI": {"importance": 1, "level": -1}, "Black Hat": {"importance": 1, "level": -1}, "security conference": {"importance": 1, "level": -1}, "Bouncer": {"importance": 2, "level": -1}, "blocker system": {"importance": 1, "level": -1}, "blocker": {"importance": 1, "level": -1}, "SpiderLabs": {"importance": 1, "level": -1}, "Trustwave": {"importance": 1, "level": -1}, "denial-of-service attacks": {"importance": 2, "level": -1}, "attack": {"importance": 1, "level": -1}, "web page": {"importance": 1, "level": -1}, "malware-masking": {"importance": 2, "level": -1}, "detect apps": {"importance": 3, "level": -1}, "malware-masking techniques": {"importance": 1, "level": -1}, "Check": {"importance": 1, "level": -1}, "security firm": {"importance": 1, "level": -1}, "apps": {"importance": 1, "level": -1}, "botnet": {"importance": 2, "level": -1}, "FalseGuide": {"importance": 1, "level": -1}, "Sophos": {"importance": 1, "level": -1}, "security company": {"importance": 1, "level": -1}, "Google Play Protect": {"importance": 2, "level": -1}, "Tekya": {"importance": 1, "level": -1}, "VirusTotal": {"importance": 1, "level": -1}, "adware": {"importance": 1, "level": -1}, "trojan": {"importance": 3, "level": -1}, "GriftHorse": {"importance": 1, "level": -1}, "third-party repositories": {"importance": 1, "level": -1}, "dropper": {"importance": 1, "level": -1}, "malware dropper": {"importance": 1, "level": -1}, "patent troll": {"importance": 1, "level": -1}, "patent infringement": {"importance": 2, "level": -1}, "patent trolls": {"importance": 1, "level": -1}, "artificial intelligence": {"importance": 4, "level": -1}, "online advertising": {"importance": 3, "level": -1}, "search engine": {"importance": 3, "level": -1}, "cloud computing": {"importance": 2, "level": -1}, "computer software": {"importance": 2, "level": -1}, "consumer electronics": {"importance": 1, "level": -1}, "September 4, 1998": {"importance": 5, "level": -1}, "Alphabet Inc.": {"importance": 37, "level": -1}, "Larry Page": {"importance": 16, "level": -1}, "computer scientists": {"importance": 2, "level": -1}, "computer scientist": {"importance": 1, "level": -1}, "Stanford University": {"importance": 1, "level": -1}, "Gmail": {"importance": 7, "level": -1}, "Waze": {"importance": 3, "level": -1}, "Chrome": {"importance": 4, "level": -1}, "YouTube": {"importance": 6, "level": -1}, "Drive": {"importance": 1, "level": -1}, "Meet": {"importance": 1, "level": -1}, "Nest": {"importance": 1, "level": -1}, "Maps": {"importance": 2, "level": -1}, "Workspace": {"importance": 1, "level": -1}, "Google Assistant": {"importance": 1, "level": -1}, "Waymo": {"importance": 6, "level": -1}, "self-driving cars": {"importance": 10, "level": -1}, "Google Self-Driving Car Project": {"importance": 3, "level": -1}, "Sidewalk Labs": {"importance": 1, "level": -1}, "mobile operating system": {"importance": 8, "level": -1}, "Willow Garage": {"importance": 3, "level": -1}, "2006": {"importance": 3, "level": -1}, "PageRank": {"importance": 8, "level": -1}, "algorithm": {"importance": 1, "level": -1}, "Google Search engine": {"importance": 1, "level": -1}, "1998": {"importance": 2, "level": -1}, "Rajeev Motwani": {"importance": 1, "level": -1}, "Terry Winograd": {"importance": 1, "level": -1}, "Baidu": {"importance": 5, "level": -1}, "Robin Li": {"importance": 4, "level": -1}, "RankDex": {"importance": 1, "level": -1}, "Sun Microsystems": {"importance": 5, "level": -1}, "Andy Bechtolsheim": {"importance": 9, "level": -1}, "Granite": {"importance": 4, "level": -1}, "Cisco": {"importance": 1, "level": -1}, "Amazon": {"importance": 5, "level": -1}, "Jeff Bezos": {"importance": 7, "level": -1}, "his wife": {"importance": 2, "level": -1}, "Craig Silverstein": {"importance": 2, "level": -1}, "Stanford": {"importance": 1, "level": -1}, "Menlo Park, California": {"importance": 2, "level": -1}, "Kleiner Perkins": {"importance": 4, "level": -1}, "venture capital": {"importance": 5, "level": -1}, "Sequoia Capital": {"importance": 3, "level": -1}, "Silicon Valley": {"importance": 4, "level": -1}, "California": {"importance": 3, "level": -1}, "Palo Alto, California": {"importance": 2, "level": -1}, "Silicon Graphics": {"importance": 2, "level": -1}, "Mountain View, California": {"importance": 4, "level": -1}, "Amphitheatre Parkway": {"importance": 2, "level": -1}, "Eric Schmidt": {"importance": 4, "level": -1}, "chairman and CEO of Google": {"importance": 2, "level": -1}, "John Doerr": {"importance": 1, "level": -1}, "chairman and CEO": {"importance": 1, "level": -1}, "Michael Moritz": {"importance": 2, "level": -1}, "Novell": {"importance": 2, "level": -1}, "chief executive officer": {"importance": 1, "level": -1}, "August 19, 2004": {"importance": 4, "level": -1}, "Initial public offering": {"importance": 1, "level": -1}, "public company": {"importance": 1, "level": -1}, "Sergey Brin": {"importance": 2, "level": -1}, "November 13, 2006": {"importance": 3, "level": -1}, "DoubleClick": {"importance": 4, "level": -1}, "March 11, 2008": {"importance": 2, "level": -1}, "May 2012": {"importance": 6, "level": -1}, "June 2013": {"importance": 6, "level": -1}, "Calico": {"importance": 4, "level": -1}, "September 19, 2013": {"importance": 3, "level": -1}, "Arthur Levinson": {"importance": 2, "level": -1}, "Apple Inc.": {"importance": 1, "level": -1}, "AlphaGo": {"importance": 4, "level": -1}, "Go": {"importance": 2, "level": -1}, "DeepMind": {"importance": 2, "level": -1}, "Sundar Pichai": {"importance": 8, "level": -1}, "CEO of Google": {"importance": 2, "level": -1}, "CEO of Alphabet": {"importance": 1, "level": -1}, "August 10, 2015": {"importance": 2, "level": -1}, "Google CEO": {"importance": 3, "level": -1}, "How Google Protected Andy Rubin, the 'Father of Android'": {"importance": 4, "level": -1}, "The New York Times": {"importance": 3, "level": -1}, "October 25, 2018": {"importance": 1, "level": -1}, "CEO": {"importance": 1, "level": -1}, "Google Stadia": {"importance": 5, "level": -1}, "March 19, 2019": {"importance": 2, "level": -1}, "Bill Ready": {"importance": 2, "level": -1}, "PayPal": {"importance": 2, "level": -1}, "COVID-19 pandemic": {"importance": 3, "level": -1}, "Google Pay": {"importance": 1, "level": -1}, "2020 Google services outages": {"importance": 2, "level": -1}, "Alphabet Workers Union": {"importance": 4, "level": -1}, "2021": {"importance": 4, "level": -1}, "March 2021": {"importance": 1, "level": -1}, "targeted ads": {"importance": 3, "level": -1}, "advertisers": {"importance": 3, "level": -1}, "Raxium": {"importance": 1, "level": -1}, "MicroLED": {"importance": 3, "level": -1}, "display technology": {"importance": 1, "level": -1}, "AI": {"importance": 1, "level": -1}, "already operational center": {"importance": 1, "level": -1}, "data center": {"importance": 2, "level": -1}, "already operational center near Columbus": {"importance": 1, "level": -1}, "2002": {"importance": 3, "level": -1}, "Google Books": {"importance": 2, "level": -1}, "Froogle": {"importance": 1, "level": -1}, "Google Cloud": {"importance": 3, "level": -1}, "AdMob": {"importance": 5, "level": -1}, "AdSense": {"importance": 7, "level": -1}, "Google AdSense": {"importance": 2, "level": -1}, "Google Ads": {"importance": 3, "level": -1}, "Google Calendar": {"importance": 4, "level": -1}, "Google Maps": {"importance": 3, "level": -1}, "Google Drive": {"importance": 3, "level": -1}, "Google Docs": {"importance": 2, "level": -1}, "Sheets": {"importance": 2, "level": -1}, "Slides": {"importance": 2, "level": -1}, "Google Photos": {"importance": 2, "level": -1}, "Google Earth": {"importance": 1, "level": -1}, "2005": {"importance": 1, "level": -1}, "Google Keep": {"importance": 2, "level": -1}, "note-taking": {"importance": 2, "level": -1}, "Google Translate": {"importance": 1, "level": -1}, "language translation": {"importance": 1, "level": -1}, "Google Chrome": {"importance": 6, "level": -1}, "web browser": {"importance": 6, "level": -1}, "Chromebook": {"importance": 3, "level": -1}, "Chromecast dongle": {"importance": 2, "level": -1}, "Google Home": {"importance": 3, "level": -1}, "Google Nest": {"importance": 15, "level": -1}, "Google Home Mini": {"importance": 3, "level": -1}, "Google Home Max": {"importance": 3, "level": -1}, "Google Home Hub": {"importance": 3, "level": -1}, "Nest Hub": {"importance": 1, "level": -1}, "Nest Audio": {"importance": 1, "level": -1}, "Nest Mini": {"importance": 1, "level": -1}, "Givitus": {"importance": 6, "level": -1}, "BigQuery": {"importance": 4, "level": -1}, "Google Cloud Platform": {"importance": 5, "level": -1}, "Google Analytics 360 Suite": {"importance": 2, "level": -1}, "March 15, 2016": {"importance": 1, "level": -1}, "Google Fiber": {"importance": 1, "level": -1}, "Project Fi": {"importance": 2, "level": -1}, "mobile virtual network operator": {"importance": 1, "level": -1}, "April 2015": {"importance": 1, "level": -1}, "OpenWallet Foundation": {"importance": 1, "level": -1}, "digital wallets": {"importance": 1, "level": -1}, "initial public offering": {"importance": 1, "level": -1}, "Google's initial public offering": {"importance": 1, "level": -1}, "Alphabet Inc": {"importance": 10, "level": -1}, "market capitalization": {"importance": 3, "level": -1}, "third quarter of 2013": {"importance": 1, "level": -1}, "2013": {"importance": 1, "level": -1}, "Google tax": {"importance": 2, "level": -1}, "tax avoidance": {"importance": 3, "level": -1}, "Multinational tax schemes": {"importance": 1, "level": -1}, "Public Accounts Committee": {"importance": 4, "level": -1}, "UK House of Commons": {"importance": 4, "level": -1}, "googol": {"importance": 1, "level": -1}, "Alphabet": {"importance": 4, "level": -1}, "Google logo": {"importance": 3, "level": -1}, "Google MentalPlex": {"importance": 3, "level": -1}, "April 1, 2000": {"importance": 3, "level": -1}, "TiSP": {"importance": 1, "level": -1}, "2007": {"importance": 1, "level": -1}, "Bork bork bork": {"importance": 2, "level": -1}, "easter eggs": {"importance": 9, "level": -1}, "Pig Latin": {"importance": 2, "level": -1}, "Hacker": {"importance": 2, "level": -1}, "leetspeak": {"importance": 2, "level": -1}, "Elmer Fudd": {"importance": 1, "level": -1}}, [[{"head": "Google Play", "type": "instance of", "tail": "app store"}, 9], [{"head": "Google Play", "type": "operating system", "tail": "Android operating system"}, 10], [{"head": "Google Play", "type": "operating system", "tail": "ChromeOS"}, 4], [{"head": "Google Play", "type": "operating system", "tail": "Android"}, 13], [{"head": "Google Play Store", "type": "operating system", "tail": "Android"}, 15], [{"head": "Google Play", "type": "inception", "tail": "March 6, 2012"}, 3], [{"head": "Google Play", "type": "replaces", "tail": "Android Market"}, 5], [{"head": "Google Play", "type": "replaces", "tail": "Google Music"}, 2], [{"head": "Google Play", "type": "replaces", "tail": "Google Movies"}, 1], [{"head": "Google Play", "type": "replaces", "tail": "Google eBookstore"}, 2], [{"head": "Android Market", "type": "replaced by", "tail": "Google Play"}, 2], [{"head": "Google Play", "type": "has part", "tail": "Android Market"}, 1], [{"head": "Google Play", "type": "has part", "tail": "Google Music"}, 1], [{"head": "Google Play", "type": "has part", "tail": "Google Movies"}, 1], [{"head": "Google Play", "type": "has part", "tail": "Google eBookstore"}, 1], [{"head": "Android Market", "type": "part of", "tail": "Google Play"}, 1], [{"head": "YouTube Music", "type": "inception", "tail": "2020"}, 1], [{"head": "YouTube Music", "type": "replaces", "tail": "Play Music"}, 2], [{"head": "YouTube Music", "type": "replaced by", "tail": "Google Play"}, 1], [{"head": "Google Play", "type": "replaces", "tail": "YouTube Music"}, 1], [{"head": "Android Market", "type": "replaced", "tail": "Google Play"}, 1], [{"head": "Google eBookstore", "type": "inception", "tail": "December 6, 2010"}, 2], [{"head": "Google Music", "type": "inception", "tail": "November 2011"}, 1], [{"head": "Google Play Store", "type": "developer", "tail": "Google"}, 4], [{"head": "Google Play Store", "type": "operating system", "tail": "ChromeOS"}, 1], [{"head": "YouTube Music", "type": "instance of", "tail": "online music locker"}, 2], [{"head": "YouTube Music", "type": "use", "tail": "online music locker"}, 1], [{"head": "Google Podcasts", "type": "instance of", "tail": "online music locker"}, 1], [{"head": "Google Play Newsstand", "type": "replaced by", "tail": "Google News"}, 2], [{"head": "Google News & Weather", "type": "replaced by", "tail": "Google News"}, 3], [{"head": "Google News", "type": "inception", "tail": "May 15, 2018"}, 3], [{"head": "Google News", "type": "replaces", "tail": "Google News & Weather"}, 3], [{"head": "Google Play Newsstand", "type": "instance of", "tail": "news aggregator"}, 1], [{"head": "Google News", "type": "replaces", "tail": "Google Play Newsstand"}, 1], [{"head": "Google Store", "type": "inception", "tail": "March 11, 2015"}, 3], [{"head": "Google Nexus", "type": "manufacturer", "tail": "Google"}, 2], [{"head": "Chromecast", "type": "manufacturer", "tail": "Google"}, 1], [{"head": "St. Patrick's Cathedral", "type": "different from", "tail": "St. Patrick's Cathedral"}, 3], [{"head": "St. Paul's Cathedral", "type": "different from", "tail": "St. Paul's Cathedral"}, 1], [{"head": "Free App of the Week", "type": "inception", "tail": "March 2017"}, 1], [{"head": "Free App of the Week", "type": "publication date", "tail": "March 2017"}, 1], [{"head": "fitness", "type": "instance of", "tail": "themes"}, 2], [{"head": "fitness", "type": "instance of", "tail": "theme"}, 1], [{"head": "puzzle game", "type": "instance of", "tail": "themes"}, 1], [{"head": "Android Market", "type": "inception", "tail": "February 2011"}, 1], [{"head": "Google Play Console", "type": "part of", "tail": "Google Play"}, 1], [{"head": "Google Play", "type": "part of", "tail": "Android Market"}, 1], [{"head": "Android Market", "type": "operating system", "tail": "Android"}, 4], [{"head": "Android Market", "type": "product or material produced", "tail": "Android app"}, 1], [{"head": "Material Design", "type": "instance of", "tail": "design language"}, 2], [{"head": "Play apps", "type": "developer", "tail": "Google"}, 2], [{"head": "PNG", "type": "based on", "tail": "WebP"}, 1], [{"head": "PNG", "type": "replaces", "tail": "WebP"}, 1], [{"head": "PNG", "type": "based on", "tail": "WebP format"}, 1], [{"head": "Google Play Instant", "type": "inception", "tail": "2017"}, 1], [{"head": "Google Play Instant", "type": "publication date", "tail": "2017"}, 1], [{"head": "Google Instant", "type": "inception", "tail": "2017"}, 1], [{"head": "Google Play payment system", "type": "inception", "tail": "February 13, 2009"}, 1], [{"head": "Google Play", "type": "inception", "tail": "February 13, 2009"}, 1], [{"head": "Google Play payment system", "type": "part of", "tail": "Google Play"}, 1], [{"head": "Google Play", "type": "inception", "tail": "September 2014"}, 1], [{"head": "Google Play", "type": "developer", "tail": "Google"}, 9], [{"head": "China UnionPay", "type": "country", "tail": "China"}, 1], [{"head": "Google", "type": "owner of", "tail": "Google Play Store"}, 1], [{"head": "Google Play Store", "type": "owned by", "tail": "Google"}, 1], [{"head": "Hong Kong", "type": "diplomatic relation", "tail": "Macau"}, 1], [{"head": "Macau", "type": "diplomatic relation", "tail": "Hong Kong"}, 1], [{"head": "Google Play gift cards", "type": "inception", "tail": "August 21, 2012"}, 1], [{"head": "Google", "type": "subsidiary", "tail": "Google Play"}, 1], [{"head": "change of the same model", "type": "named after", "tail": "Apple"}, 1], [{"head": "change of the same model", "type": "named after", "tail": "Apple's"}, 1], [{"head": "Google Play", "type": "end time", "tail": "January 1, 2018"}, 1], [{"head": "Google Play Store", "type": "instance of", "tail": "app store"}, 4], [{"head": "App Store", "type": "instance of", "tail": "app store"}, 1], [{"head": "", "type": "operating system", "tail": "Microsoft Windows"}, 1], [{"head": "Google Play Store", "type": "part of", "tail": "Android Market"}, 1], [{"head": "Google Play Store", "type": "developer", "tail": "Android Open Source Project"}, 1], [{"head": "Google Play Awards", "type": "inception", "tail": "April 2016"}, 1], [{"head": "Google Play Services", "type": "instance of", "tail": "API"}, 1], [{"head": "Google Play Services", "type": "operating system", "tail": "Android 2.2 \"Froyo\""}, 1], [{"head": "Google Play", "type": "owned by", "tail": "Google"}, 2], [{"head": "Disney+", "type": "publication date", "tail": "2020"}, 1], [{"head": "Google Play", "type": "inception", "tail": "June 2017"}, 3], [{"head": "ESRB", "type": "instance of", "tail": "ratings authority"}, 1], [{"head": "Google", "type": "subsidiary", "tail": "Google Play Store"}, 1], [{"head": "PEGI", "type": "applies to jurisdiction", "tail": "Europe"}, 1], [{"head": "PEGI", "type": "operating area", "tail": "Europe"}, 1], [{"head": "PEGI", "type": "continent", "tail": "Europe"}, 1], [{"head": "Play Store", "type": "developer", "tail": "Google"}, 4], [{"head": "Google", "type": "subsidiary", "tail": "Play Store"}, 1], [{"head": "Google", "type": "owner of", "tail": "Play Store"}, 1], [{"head": "Android Market", "type": "developer", "tail": "Google"}, 5], [{"head": "Gro", "type": "part of", "tail": "Android Market"}, 1], [{"head": "Grooveshark", "type": "operating system", "tail": "Android"}, 3], [{"head": "Google", "type": "subsidiary", "tail": "App Market"}, 1], [{"head": "App Market", "type": "parent organization", "tail": "Google"}, 1], [{"head": "Google Play Store", "type": "operator", "tail": "Google"}, 1], [{"head": "Android Marshmallow", "type": "distributed by", "tail": "Google Play Store"}, 1], [{"head": "spyware", "type": "subclass of", "tail": "malware"}, 4], [{"head": "Google Bouncer", "type": "inception", "tail": "February 2012"}, 1], [{"head": "Play Protect", "type": "inception", "tail": "February 2012"}, 1], [{"head": "trojan horses", "type": "subclass of", "tail": "malware"}, 1], [{"head": "trojan horse", "type": "subclass of", "tail": "malware"}, 1], [{"head": "DroidDream", "type": "instance of", "tail": "exploit"}, 1], [{"head": "DroidDream", "type": "instance of", "tail": "rootkit exploit"}, 1], [{"head": "DroidDream", "type": "instance of", "tail": "rootkit"}, 1], [{"head": "Gingerbread", "type": "subclass of", "tail": "Android"}, 2], [{"head": "Android", "type": "has part", "tail": "Gingerbread"}, 1], [{"head": "IMSI", "type": "uses", "tail": "IMEI"}, 1], [{"head": "Black Hat", "type": "instance of", "tail": "security conference"}, 1], [{"head": "Bouncer", "type": "instance of", "tail": "blocker system"}, 1], [{"head": "Bouncer", "type": "instance of", "tail": "blocker"}, 1], [{"head": "SpiderLabs", "type": "parent organization", "tail": "Trustwave"}, 1], [{"head": "denial-of-service attacks", "type": "subclass of", "tail": "attack"}, 1], [{"head": "denial-of-service attacks", "type": "uses", "tail": "web page"}, 1], [{"head": "malware-masking", "type": "subclass of", "tail": "detect apps"}, 1], [{"head": "malware-masking techniques", "type": "subclass of", "tail": "detect apps"}, 1], [{"head": "malware-masking", "type": "use", "tail": "detect apps"}, 1], [{"head": "Check", "type": "instance of", "tail": "security firm"}, 1], [{"head": "Google Play", "type": "instance of", "tail": "apps"}, 1], [{"head": "botnet", "type": "subclass of", "tail": "malware"}, 1], [{"head": "FalseGuide", "type": "instance of", "tail": "botnet"}, 1], [{"head": "Sophos", "type": "instance of", "tail": "security company"}, 1], [{"head": "Google Play Protect", "type": "part of", "tail": "Google Play"}, 2], [{"head": "Tekya", "type": "instance of", "tail": "malware"}, 1], [{"head": "VirusTotal", "type": "part of", "tail": "Google Play"}, 1], [{"head": "adware", "type": "subclass of", "tail": "trojan"}, 1], [{"head": "Google Play", "type": "has part", "tail": "Google Play Store"}, 1], [{"head": "Google Play Store", "type": "part of", "tail": "Google Play"}, 1], [{"head": "Google Play", "type": "different from", "tail": "Google Play Store"}, 1], [{"head": "Google Play Store", "type": "different from", "tail": "Google Play"}, 1], [{"head": "Google", "type": "product or material produced", "tail": "Android"}, 2], [{"head": "Play Store", "type": "operating system", "tail": "Android"}, 1], [{"head": "GriftHorse", "type": "instance of", "tail": "trojan"}, 1], [{"head": "Google Play Store", "type": "instance of", "tail": "third-party repositories"}, 1], [{"head": "dropper", "type": "subclass of", "tail": "malware"}, 1], [{"head": "malware dropper", "type": "subclass of", "tail": "trojan"}, 1], [{"head": "patent troll", "type": "field of this occupation", "tail": "patent infringement"}, 1], [{"head": "patent trolls", "type": "field of work", "tail": "patent infringement"}, 1], [{"head": "Google", "type": "product or material produced", "tail": "artificial intelligence"}, 3], [{"head": "Google", "type": "product or material produced", "tail": "online advertising"}, 3], [{"head": "Google", "type": "product or material produced", "tail": "search engine"}, 3], [{"head": "Google", "type": "product or material produced", "tail": "cloud computing"}, 2], [{"head": "Google", "type": "product or material produced", "tail": "computer software"}, 2], [{"head": "Google", "type": "product or material produced", "tail": "consumer electronics"}, 1], [{"head": "Google", "type": "product", "tail": "artificial intelligence"}, 1], [{"head": "Google", "type": "inception", "tail": "September 4, 1998"}, 5], [{"head": "Google", "type": "parent organization", "tail": "Alphabet Inc."}, 20], [{"head": "Larry Page", "type": "employer", "tail": "Google"}, 7], [{"head": "Larry Page", "type": "employer", "tail": "computer scientists"}, 1], [{"head": "Larry Page", "type": "employer", "tail": "computer scientist"}, 1], [{"head": "Google", "type": "founded by", "tail": "Larry Page"}, 3], [{"head": "Larry Page", "type": "occupation", "tail": "computer scientists"}, 1], [{"head": "Larry Page", "type": "educated at", "tail": "Stanford University"}, 1], [{"head": "Alphabet Inc.", "type": "subsidiary", "tail": "Google"}, 14], [{"head": "Google", "type": "owner of", "tail": "Gmail"}, 4], [{"head": "Google", "type": "owner of", "tail": "Waze"}, 1], [{"head": "Google", "type": "owner of", "tail": "Chrome"}, 1], [{"head": "Google", "type": "owner of", "tail": "YouTube"}, 1], [{"head": "Google", "type": "owner of", "tail": "Drive"}, 1], [{"head": "Google", "type": "owner of", "tail": "Meet"}, 1], [{"head": "Google", "type": "owner of", "tail": "Nest"}, 1], [{"head": "Gmail", "type": "owned by", "tail": "Google"}, 3], [{"head": "Waze", "type": "owned by", "tail": "Google"}, 2], [{"head": "Maps", "type": "owned by", "tail": "Google"}, 2], [{"head": "Chrome", "type": "developer", "tail": "Google"}, 2], [{"head": "YouTube", "type": "owned by", "tail": "Google"}, 2], [{"head": "Workspace", "type": "developer", "tail": "Google"}, 1], [{"head": "Google Assistant", "type": "developer", "tail": "Google"}, 1], [{"head": "Waymo", "type": "instance of", "tail": "self-driving cars"}, 4], [{"head": "Google Self-Driving Car Project", "type": "instance of", "tail": "self-driving cars"}, 2], [{"head": "Waymo", "type": "subclass of", "tail": "self-driving cars"}, 2], [{"head": "Google Self-Driving Car Project", "type": "subclass of", "tail": "self-driving cars"}, 1], [{"head": "Sidewalk Labs", "type": "instance", "tail": "self-driving cars"}, 1], [{"head": "Google", "type": "product or material produced", "tail": "mobile operating system"}, 5], [{"head": "Willow Garage", "type": "inception", "tail": "2006"}, 3], [{"head": "PageRank", "type": "instance of", "tail": "algorithm"}, 1], [{"head": "Google Search engine", "type": "owned by", "tail": "Google"}, 1], [{"head": "PageRank", "type": "inception", "tail": "1998"}, 1], [{"head": "PageRank", "type": "developer", "tail": "Rajeev Motwani"}, 1], [{"head": "PageRank", "type": "developer", "tail": "Terry Winograd"}, 1], [{"head": "PageRank", "type": "publication date", "tail": "1998"}, 1], [{"head": "Baidu", "type": "founded by", "tail": "Robin Li"}, 3], [{"head": "RankDex", "type": "developer", "tail": "Robin Li"}, 1], [{"head": "Baidu", "type": "different from", "tail": "Baidu"}, 1], [{"head": "Sun Microsystems", "type": "founded by", "tail": "Andy Bechtolsheim"}, 3], [{"head": "Andy Bechtolsheim", "type": "employer", "tail": "Sun Microsystems"}, 2], [{"head": "Google", "type": "founded by", "tail": "Andy Bechtolsheim"}, 1], [{"head": "Granite", "type": "founded by", "tail": "Andy Bechtolsheim"}, 2], [{"head": "Andy Bechtolsheim", "type": "employer", "tail": "Granite"}, 1], [{"head": "Granite", "type": "parent organization", "tail": "Cisco"}, 1], [{"head": "Amazon", "type": "founded by", "tail": "Jeff Bezos"}, 3], [{"head": "Jeff Bezos", "type": "employer", "tail": "Amazon"}, 2], [{"head": "Jeff Bezos", "type": "spouse", "tail": "his wife"}, 1], [{"head": "his wife", "type": "spouse", "tail": "Jeff Bezos"}, 1], [{"head": "Craig Silverstein", "type": "educated at", "tail": "Stanford"}, 1], [{"head": "Craig Silverstein", "type": "residence", "tail": "Menlo Park, California"}, 1], [{"head": "Google", "type": "headquarters location", "tail": "Menlo Park, California"}, 1], [{"head": "Kleiner Perkins", "type": "product or material produced", "tail": "venture capital"}, 2], [{"head": "Sequoia Capital", "type": "product or material produced", "tail": "venture capital"}, 1], [{"head": "Kleiner Perkins", "type": "industry", "tail": "venture capital"}, 1], [{"head": "Sequoia Capital", "type": "industry", "tail": "venture capital"}, 1], [{"head": "Silicon Valley", "type": "located in the administrative territorial entity", "tail": "California"}, 2], [{"head": "Palo Alto, California", "type": "part of", "tail": "Silicon Valley"}, 2], [{"head": "Silicon Graphics", "type": "headquarters location", "tail": "Mountain View, California"}, 2], [{"head": "Amphitheatre Parkway", "type": "located in the administrative territorial entity", "tail": "Mountain View, California"}, 2], [{"head": "Eric Schmidt", "type": "position held", "tail": "chairman and CEO of Google"}, 2], [{"head": "John Doerr", "type": "employer", "tail": "Kleiner Perkins"}, 1], [{"head": "Eric Schmidt", "type": "position held", "tail": "chairman and CEO"}, 1], [{"head": "Michael Moritz", "type": "employer", "tail": "Sequoia Capital"}, 1], [{"head": "Novell", "type": "office held by head of the organization", "tail": "chief executive officer"}, 1], [{"head": "Michael Moritz", "type": "employer", "tail": "Novell"}, 1], [{"head": "Google", "type": "inception", "tail": "August 19, 2004"}, 3], [{"head": "Initial public offering", "type": "subclass of", "tail": "public company"}, 1], [{"head": "Google", "type": "founded by", "tail": "Sergey Brin"}, 1], [{"head": "Google", "type": "founded by", "tail": "Eric Schmidt"}, 1], [{"head": "YouTube", "type": "inception", "tail": "November 13, 2006"}, 3], [{"head": "DoubleClick", "type": "end time", "tail": "March 11, 2008"}, 1], [{"head": "DoubleClick", "type": "dissolved, abolished or demolished date", "tail": "March 11, 2008"}, 1], [{"head": "May 2012", "type": "point in time", "tail": "May 2012"}, 3], [{"head": "June 2013", "type": "point in time", "tail": "June 2013"}, 3], [{"head": "Calico", "type": "inception", "tail": "September 19, 2013"}, 3], [{"head": "Arthur Levinson", "type": "employer", "tail": "Apple Inc."}, 1], [{"head": "Calico", "type": "founded by", "tail": "Arthur Levinson"}, 1], [{"head": "AlphaGo", "type": "sport", "tail": "Go"}, 2], [{"head": "AlphaGo", "type": "developer", "tail": "DeepMind"}, 2], [{"head": "Sundar Pichai", "type": "position held", "tail": "CEO of Google"}, 1], [{"head": "CEO of Google", "type": "officeholder", "tail": "Sundar Pichai"}, 1], [{"head": "Larry Page", "type": "position held", "tail": "CEO of Alphabet"}, 1], [{"head": "Alphabet Inc.", "type": "inception", "tail": "August 10, 2015"}, 2], [{"head": "Sundar Pichai", "type": "position held", "tail": "Google CEO"}, 2], [{"head": "Google CEO", "type": "officeholder", "tail": "Sundar Pichai"}, 1], [{"head": "Google", "type": "founded by", "tail": "Sundar Pichai"}, 1], [{"head": "Sundar Pichai", "type": "employer", "tail": "Google"}, 1], [{"head": "How Google Protected Andy Rubin, the 'Father of Android'", "type": "published in", "tail": "The New York Times"}, 3], [{"head": "How Google Protected Andy Rubin, the 'Father of Android'", "type": "publication date", "tail": "October 25, 2018"}, 1], [{"head": "Sundar Pichai", "type": "position held", "tail": "CEO"}, 1], [{"head": "Google Stadia", "type": "inception", "tail": "March 19, 2019"}, 2], [{"head": "Bill Ready", "type": "employer", "tail": "PayPal"}, 2], [{"head": "COVID-19 pandemic", "type": "point in time", "tail": "2020"}, 3], [{"head": "Google Pay", "type": "developer", "tail": "Google"}, 1], [{"head": "2020 Google services outages", "type": "point in time", "tail": "2020"}, 2], [{"head": "Alphabet Workers Union", "type": "inception", "tail": "2021"}, 4], [{"head": "Google Stadia", "type": "developer", "tail": "Google"}, 1], [{"head": "Google Stadia", "type": "owned by", "tail": "Google"}, 1], [{"head": "Google Stadia", "type": "publication date", "tail": "March 2021"}, 1], [{"head": "targeted ads", "type": "subclass of", "tail": "advertisers"}, 1], [{"head": "targeted ads", "type": "facet of", "tail": "advertisers"}, 1], [{"head": "targeted ads", "type": "instance of", "tail": "advertisers"}, 1], [{"head": "Raxium", "type": "product or material produced", "tail": "MicroLED"}, 1], [{"head": "MicroLED", "type": "located in the administrative territorial entity", "tail": "California"}, 1], [{"head": "MicroLED", "type": "instance of", "tail": "display technology"}, 1], [{"head": "Google", "type": "product or material produced", "tail": "AI"}, 1], [{"head": "already operational center", "type": "instance of", "tail": "data center"}, 1], [{"head": "already operational center near Columbus", "type": "instance of", "tail": "data center"}, 1], [{"head": "Google News", "type": "inception", "tail": "2002"}, 2], [{"head": "Google Books", "type": "owned by", "tail": "Google"}, 2], [{"head": "Froogle", "type": "inception", "tail": "2002"}, 1], [{"head": "Google Cloud", "type": "parent organization", "tail": "Google"}, 1], [{"head": "Google", "type": "subsidiary", "tail": "Google Cloud"}, 2], [{"head": "AdMob", "type": "product or material produced", "tail": "AdSense"}, 1], [{"head": "AdMob", "type": "part of", "tail": "AdSense"}, 2], [{"head": "AdSense", "type": "has part", "tail": "AdMob"}, 2], [{"head": "AdSense", "type": "has part", "tail": "DoubleClick"}, 1], [{"head": "DoubleClick", "type": "part of", "tail": "AdSense"}, 1], [{"head": "Google AdSense", "type": "owned by", "tail": "Google"}, 1], [{"head": "Google AdSense", "type": "instance of", "tail": "Google Ads"}, 1], [{"head": "Google Ads", "type": "owned by", "tail": "Google"}, 1], [{"head": "Google", "type": "owner of", "tail": "Google Ads"}, 1], [{"head": "Google", "type": "owner of", "tail": "Google Calendar"}, 3], [{"head": "Google", "type": "owner of", "tail": "Google Maps"}, 3], [{"head": "Google", "type": "owner of", "tail": "Google Drive"}, 3], [{"head": "Google", "type": "owner of", "tail": "Google Docs"}, 2], [{"head": "Google", "type": "owner of", "tail": "Sheets"}, 2], [{"head": "Google", "type": "owner of", "tail": "Slides"}, 2], [{"head": "Google", "type": "owner of", "tail": "Google Photos"}, 2], [{"head": "Google Calendar", "type": "owned by", "tail": "Google"}, 1], [{"head": "Google Earth", "type": "inception", "tail": "2005"}, 1], [{"head": "Google Keep", "type": "use", "tail": "note-taking"}, 2], [{"head": "Google Translate", "type": "use", "tail": "language translation"}, 1], [{"head": "Android", "type": "instance of", "tail": "mobile operating system"}, 3], [{"head": "Android", "type": "derivative work", "tail": "ChromeOS"}, 3], [{"head": "Google Chrome", "type": "instance of", "tail": "web browser"}, 3], [{"head": "Google Chrome", "type": "operating system", "tail": "ChromeOS"}, 3], [{"head": "ChromeOS", "type": "based on", "tail": "Android"}, 3], [{"head": "ChromeOS", "type": "instance of", "tail": "web browser"}, 3], [{"head": "ChromeOS", "type": "instance of", "tail": "Chrome"}, 1], [{"head": "Chromebook", "type": "operating system", "tail": "ChromeOS"}, 3], [{"head": "Chromecast", "type": "has part", "tail": "Chromecast dongle"}, 1], [{"head": "Chromecast", "type": "uses", "tail": "Chromecast dongle"}, 1], [{"head": "Google Home", "type": "manufacturer", "tail": "Google Nest"}, 3], [{"head": "Google Home Mini", "type": "manufacturer", "tail": "Google Nest"}, 3], [{"head": "Google Home Max", "type": "manufacturer", "tail": "Google Nest"}, 3], [{"head": "Google Home Hub", "type": "manufacturer", "tail": "Google Nest"}, 3], [{"head": "Nest Hub", "type": "manufacturer", "tail": "Google Nest"}, 1], [{"head": "Nest Audio", "type": "manufacturer", "tail": "Google Nest"}, 1], [{"head": "Nest Mini", "type": "manufacturer", "tail": "Google Nest"}, 1], [{"head": "Givitus", "type": "has effectivitusivitusivitusivitusivitusivitusivitusivitusivitusivitusivitusivitusivitusivitusivitusivitusivitusivitusivitusivitusivitusivitusivitusivitusiv", "tail": "Givitus"}, 1], [{"head": "Givitus", "type": "has effectivitusivitusivitusivitusivitusivitusitusivitusivitusivitusivitusivitusivitusivitusivitusivitusivitusivitusivitusivitusivitusivitusivitusivitusivitus", "tail": "Givitus"}, 1], [{"head": "Givitus", "type": "has effectivivitusivitusivitusivitusivitusivitusivitusivitusivitusivitusivitusivitusivitusivitusivitusivitusivitusivitusivitusivitusivitusivitusivitusivitus", "tail": "Givitus"}, 1], [{"head": "BigQuery", "type": "part of", "tail": "Google Cloud Platform"}, 3], [{"head": "Google Cloud Platform", "type": "has part", "tail": "BigQuery"}, 1], [{"head": "Google Analytics 360 Suite", "type": "inception", "tail": "March 15, 2016"}, 1], [{"head": "Google Analytics 360 Suite", "type": "part of", "tail": "Google Cloud Platform"}, 1], [{"head": "Google Fiber", "type": "parent organization", "tail": "Alphabet Inc."}, 1], [{"head": "Project Fi", "type": "instance of", "tail": "mobile virtual network operator"}, 1], [{"head": "Project Fi", "type": "inception", "tail": "April 2015"}, 1], [{"head": "OpenWallet Foundation", "type": "product or material produced", "tail": "digital wallets"}, 1], [{"head": "Google", "type": "instance of", "tail": "initial public offering"}, 1], [{"head": "Google's initial public offering", "type": "point in time", "tail": "August 19, 2004"}, 1], [{"head": "Alphabet Inc", "type": "subsidiary", "tail": "Google"}, 5], [{"head": "Google", "type": "parent organization", "tail": "Alphabet Inc"}, 4], [{"head": "Google", "type": "subsidiary", "tail": "Alphabet Inc"}, 1], [{"head": "Google", "type": "owned by", "tail": "Larry Page"}, 1], [{"head": "Google", "type": "instance of", "tail": "market capitalization"}, 3], [{"head": "third quarter of 2013", "type": "point in time", "tail": "2013"}, 1], [{"head": "Google tax", "type": "instance of", "tail": "tax avoidance"}, 1], [{"head": "Multinational tax schemes", "type": "subclass of", "tail": "tax avoidance"}, 1], [{"head": "Google tax", "type": "subclass of", "tail": "tax avoidance"}, 1], [{"head": "Public Accounts Committee", "type": "part of", "tail": "UK House of Commons"}, 2], [{"head": "UK House of Commons", "type": "has part", "tail": "Public Accounts Committee"}, 1], [{"head": "Public Accounts Committee", "type": "parent organization", "tail": "UK House of Commons"}, 1], [{"head": "Google", "type": "named after", "tail": "googol"}, 1], [{"head": "PageRank", "type": "owned by", "tail": "Google"}, 3], [{"head": "Google", "type": "parent organization", "tail": "Alphabet"}, 1], [{"head": "Alphabet", "type": "subsidiary", "tail": "Google"}, 1], [{"head": "Google logo", "type": "designed by", "tail": "Sergey Brin"}, 1], [{"head": "Google logo", "type": "owned by", "tail": "Alphabet"}, 1], [{"head": "Alphabet", "type": "owner of", "tail": "Google logo"}, 1], [{"head": "Google MentalPlex", "type": "inception", "tail": "April 1, 2000"}, 2], [{"head": "Google MentalPlex", "type": "publication date", "tail": "April 1, 2000"}, 1], [{"head": "TiSP", "type": "inception", "tail": "2007"}, 1], [{"head": "Bork bork bork", "type": "instance of", "tail": "easter eggs"}, 2], [{"head": "Pig Latin", "type": "instance of", "tail": "easter eggs"}, 2], [{"head": "Hacker", "type": "instance of", "tail": "easter eggs"}, 2], [{"head": "leetspeak", "type": "instance of", "tail": "easter eggs"}, 2], [{"head": "Elmer Fudd", "type": "instance of", "tail": "easter eggs"}, 1]]]